medchemfilters/__init__.py
medchemfilters/__main__.py
medchemfilters/ADMET/__init__.py
medchemfilters/ADMET/filters.py
medchemfilters/ADMET/mc_filter.py
medchemfilters-0.0.1.dist-info/METADATA
medchemfilters-0.0.1.dist-info/WHEEL
medchemfilters-0.0.1.dist-info/licenses/LICENSE
medchemfilters-0.0.1.dist-info/RECORD
