Metadata-Version: 2.3
Name: medchemfilters
Version: 0.0.1
Summary: Utility for reaction modeling using graph grammar
Project-URL: homepage, https://github.com/ThinhUMP/medchemfilters
Project-URL: source, https://github.com/ThinhUMP/medchemfilters
Project-URL: issues, https://github.com/ThinhUMP/medchemfilters/issues
Author-email: Van-Thinh To <tvthinhd19@gmail.com>
Classifier: License :: OSI Approved :: MIT License
Classifier: Operating System :: OS Independent
Classifier: Programming Language :: Python :: 3
Requires-Python: >=3.11
Requires-Dist: joblib>=1.4.2
Requires-Dist: pandas>=2.2.2
Requires-Dist: rdkit>=2024.3.3
Requires-Dist: scopy>=1.2.5
